<mujoco model="mygo2_rough">
  <include file="sizu_v1.xml" />

  <statistic center="0 0 0.1" extent="0.8" />

  <visual>
    <headlight diffuse="0.6 0.6 0.6" ambient="0.3 0.3 0.3" specular="0 0 0" />
    <rgba haze="0.15 0.25 0.35 1" />
    <global azimuth="-130" elevation="-20" />
  </visual>

  <asset>
    <texture type="skybox" builtin="gradient" rgb1="0.3 0.5 0.7" rgb2="0 0 0" width="512" height="3072" />
    <texture type="2d" name="groundplane" builtin="checker" mark="edge" rgb1="0.2 0.3 0.4" rgb2="0.1 0.2 0.3" markrgb="0.8 0.8 0.8" width="300" height="300" />
    <material name="groundplane" texture="groundplane" texuniform="true" texrepeat="5 5" reflectance="0.2" />
  <hfield name="perlin_hfield" size="1.0 0.75 0.3 0.3" file="height_field.png" /><hfield name="image_hfield" size="1.0 1.0 0.02 0.1" file="unitree_hfield.png" /></asset>

  <worldbody>
    <light pos="0 0 1.5" dir="0 0 -1" directional="true" />
    <geom name="floor" size="0 0 0.05" type="plane" material="groundplane" />
  <geom pos="1.5 0.0 0.1" type="box" size="0.5 0.75 0.05" quat="1.0 0.0 0.0 0.0" /><geom pos="1.5 0.0 0.25" type="cylinder" size="0.5 0.25 0.05" quat="1.0 0.0 0.0 0.0" /><geom pos="2.0 2.0 0.25" type="box" size="1.5 0.75 0.05" quat="0.9950041652780258 0.0 -0.09983341664682815 0.0" /><geom pos="4.0 2.0 0.55" type="box" size="0.5 0.75 0.05" quat="1.0 0.0 0.0 0.0" /><geom pos="6.0 2.0 0.25" type="box" size="1.5 0.75 0.05" quat="0.9950041652780258 0.0 0.09983341664682815 0.0" /><geom pos="1.3 4.0 0.075" type="box" size="0.15 0.75 0.075" quat="1.0 0.0 0.0 0.0" /><geom pos="1.6 4.0 0.22499999999999998" type="box" size="0.15 0.75 0.075" quat="1.0 0.0 0.0 0.0" /><geom pos="1.9 4.0 0.375" type="box" size="0.15 0.75 0.075" quat="1.0 0.0 0.0 0.0" /><geom pos="2.2 4.0 0.525" type="box" size="0.15 0.75 0.075" quat="1.0 0.0 0.0 0.0" /><geom pos="2.5 4.0 0.675" type="box" size="0.15 0.75 0.075" quat="1.0 0.0 0.0 0.0" /><geom pos="2.8 4.0 0.8250000000000001" type="box" size="0.15 0.75 0.075" quat="1.0 0.0 0.0 0.0" /><geom pos="3.1 4.0 0.9750000000000001" type="box" size="0.15 0.75 0.075" quat="1.0 0.0 0.0 0.0" /><geom pos="3.4 4.0 1.125" type="box" size="0.15 0.75 0.075" quat="1.0 0.0 0.0 0.0" /><geom pos="3.6999999999999997 4.0 1.275" type="box" size="0.15 0.75 0.075" quat="1.0 0.0 0.0 0.0" /><geom pos="3.9999999999999996 4.0 1.4249999999999998" type="box" size="0.15 0.75 0.075" quat="1.0 0.0 0.0 0.0" /><geom pos="4.299999999999999 4.0 1.275" type="box" size="0.15 0.75 0.075" quat="1.0 0.0 0.0 0.0" /><geom pos="4.6 4.0 1.125" type="box" size="0.15 0.75 0.075" quat="1.0 0.0 0.0 0.0" /><geom pos="4.899999999999999 4.0 0.975" type="box" size="0.15 0.75 0.075" quat="1.0 0.0 0.0 0.0" /><geom pos="5.199999999999999 4.0 0.825" type="box" size="0.15 0.75 0.075" quat="1.0 0.0 0.0 0.0" /><geom pos="5.499999999999999 4.0 0.6749999999999999" type="box" size="0.15 0.75 0.075" quat="1.0 0.0 0.0 0.0" /><geom pos="5.799999999999999 4.0 0.5249999999999999" type="box" size="0.15 0.75 0.075" quat="1.0 0.0 0.0 0.0" /><geom pos="6.099999999999999 4.0 0.3749999999999999" type="box" size="0.15 0.75 0.075" quat="1.0 0.0 0.0 0.0" /><geom pos="6.399999999999999 4.0 0.2249999999999999" type="box" size="0.15 0.75 0.075" quat="1.0 0.0 0.0 0.0" /><geom pos="6.699999999999998 4.0 0.0749999999999999" type="box" size="0.15 0.75 0.075" quat="1.0 0.0 0.0 0.0" /><geom pos="1.3 6.0 0.0" type="box" size="0.15 0.75 0.05" quat="1.0 0.0 0.0 0.0" /><geom pos="1.6 6.0 0.0" type="box" size="0.15 0.75 0.05" quat="1.0 0.0 0.0 0.0" /><geom pos="1.9 6.0 0.0" type="box" size="0.15 0.75 0.05" quat="1.0 0.0 0.0 0.0" /><geom pos="2.2 6.0 0.0" type="box" size="0.15 0.75 0.05" quat="1.0 0.0 0.0 0.0" /><geom pos="2.5 6.0 0.0" type="box" size="0.15 0.75 0.05" quat="1.0 0.0 0.0 0.0" /><geom pos="2.8 6.0 0.0" type="box" size="0.15 0.75 0.05" quat="1.0 0.0 0.0 0.0" /><geom pos="3.1 6.0 0.0" type="box" size="0.15 0.75 0.05" quat="1.0 0.0 0.0 0.0" /><geom pos="3.4 6.0 0.0" type="box" size="0.15 0.75 0.05" quat="1.0 0.0 0.0 0.0" /><geom pos="3.6999999999999997 6.0 0.0" type="box" size="0.15 0.75 0.05" quat="1.0 0.0 0.0 0.0" /><geom pos="3.9999999999999996 6.0 0.0" type="box" size="0.15 0.75 0.05" quat="1.0 0.0 0.0 0.0" /><geom pos="4.299999999999999 6.0 0.0" type="box" size="0.15 0.75 0.05" quat="1.0 0.0 0.0 0.0" /><geom pos="4.6 6.0 0.0" type="box" size="0.15 0.75 0.05" quat="1.0 0.0 0.0 0.0" /><geom pos="4.899999999999999 6.0 0.0" type="box" size="0.15 0.75 0.05" quat="1.0 0.0 0.0 0.0" /><geom pos="5.199999999999999 6.0 0.0" type="box" size="0.15 0.75 0.05" quat="1.0 0.0 0.0 0.0" /><geom pos="5.499999999999999 6.0 0.0" type="box" size="0.15 0.75 0.05" quat="1.0 0.0 0.0 0.0" /><geom pos="5.799999999999999 6.0 0.0" type="box" size="0.15 0.75 0.05" quat="1.0 0.0 0.0 0.0" /><geom pos="6.099999999999999 6.0 0.0" type="box" size="0.15 0.75 0.05" quat="1.0 0.0 0.0 0.0" /><geom pos="6.399999999999999 6.0 0.0" type="box" size="0.15 0.75 0.05" quat="1.0 0.0 0.0 0.0" /><geom pos="6.699999999999998 6.0 0.0" type="box" size="0.15 0.75 0.05" quat="1.0 0.0 0.0 0.0" /><geom pos="-2.3097175507979393 5.187164974784164 -0.25" type="box" size="0.2585514946206913 0.2544026629757161 0.22752340818041822" quat="0.9931983607807574 0.0647958963386486 -0.020053562071563998 -0.09463806109768526" /><geom pos="-2.3097175507979393 5.339052152503778 -0.25" type="box" size="0.26414834664662423 0.23226270465834772 0.25527981274822775" quat="0.9897526394551258 -0.09051437565321487 0.04320188865734422 0.10163885727495436" /><geom pos="-2.3097175507979393 5.5541534089615965 -0.25" type="box" size="0.23673053639014427 0.2689715283007836 0.2632175329081558" quat="0.9965812791969 0.06407500990830586 -0.05021299777453259 0.014099713260050467" /><geom pos="-2.3097175507979393 5.783068406474157 -0.25" type="box" size="0.2420179916787724 0.22704823695296972 0.2432922256103075" quat="0.9950124987315315 0.07215737804436635 -0.02481437217033611 0.06424707849846781" /><geom pos="-2.3097175507979393 6.022192811752266 -0.25" type="box" size="0.23255207235614045 0.22916403389446932 0.2323545674424687" quat="0.9959160412389965 0.014146063549039632 -0.08642366341845908 -0.021956276784672532" /><geom pos="-2.3097175507979393 6.253461390156923 -0.25" type="box" size="0.26438913608024894 0.27107466764225435 0.2437341310274999" quat="0.9986124403764393 -0.030600339060561046 -0.005129863068014265 0.042549943357127334" /><geom pos="-2.3097175507979393 6.47104088471536 -0.25" type="box" size="0.2653583944620773 0.231692606174362 0.2709504609515637" quat="0.9993011574321559 0.007475546684262893 0.007063567244891817 -0.03593631831869037" /><geom pos="-2.3097175507979393 6.659502546845579 -0.25" type="box" size="0.24159351054395195 0.2521400284091909 0.2531520031007119" quat="0.9947208271932331 -0.04014950591181577 0.04336481587283772 -0.08389270449426552" /><geom pos="-2.086467243549161 5.16423721408182 -0.25" type="box" size="0.248967406886983 0.25380327290846805 0.25227792941079946" quat="0.9935900242121506 -0.011614032562104705 0.07751191148916314 -0.081460920759838" /><geom pos="-2.086467243549161 5.379510554503311 -0.25" type="box" size="0.2595687573783483 0.2652719863514786 0.27277296318336763" quat="0.9969296860658482 0.013726934168429808 0.07623069766879946 0.011474016381069308" /><geom pos="-2.086467243549161 5.540228009761133 -0.25" type="box" size="0.24725218979015148 0.22694463127996561 0.23235105670261183" quat="0.9888421969287745 0.08740263787835564 0.0843314657792277 0.08625596990647429" /><geom pos="-2.086467243549161 5.741175941250562 -0.25" type="box" size="0.27451820250253317 0.2412436439511694 0.26675193730133323" quat="0.9993281440398124 -0.0016541401613406265 0.036471306513278776 0.003219961410525546" /><geom pos="-2.086467243549161 5.929996756891732 -0.25" type="box" size="0.2276568636565537 0.25763539098595434 0.25628500365658935" quat="0.9947129504427802 0.004636662242678193 0.037797492993095615 -0.09537293697954083" /><geom pos="-2.086467243549161 6.141761369294313 -0.25" type="box" size="0.23575719748741808 0.23608268891634182 0.25993318619260924" quat="0.9960203150791045 -0.08676807722904731 0.020204620201122823 0.002570222991109629" /><geom pos="-2.086467243549161 6.304552256817964 -0.25" type="box" size="0.22999899649072725 0.25566250833030696 0.2518540536434429" quat="0.9967143178000905 0.011619891559981142 0.04636229809317212 -0.06539177416123915" /><geom pos="-2.086467243549161 6.5178359374364625 -0.25" type="box" size="0.2462857731096567 0.26808208625088026 0.240978709471636" quat="0.9976528915716425 -0.021455805677598163 0.054959740997142965 -0.034753175552638724" /><geom pos="-1.9254301063148747 5.172772345325274 -0.25" type="box" size="0.22732465596892062 0.2547263639883602 0.24020662537361187" quat="0.9972201658772847 -0.07396986077252624 0.008966295421068096 -7.753319297807543e-05" /><geom pos="-1.9254301063148747 5.364347733755746 -0.25" type="box" size="0.2301002140031642 0.24012765960349275 0.26248523166870624" quat="0.9923737745959713 0.06245600516974688 0.04717252415577332 -0.0952275793935445" /><geom pos="-1.9254301063148747 5.601043780246969 -0.25" type="box" size="0.2274657856827303 0.2616293492527084 0.2680901311191183" quat="0.9904080324222363 -0.0906133066254699 0.09667128390184508 -0.03918955019749705" /><geom pos="-1.9254301063148747 5.79933416847244 -0.25" type="box" size="0.26478658877582745 0.2286933210947834 0.25033055859055886" quat="0.9977448451849217 0.010312849573124115 0.029605434979532018 -0.05934970311864803" /><geom pos="-1.9254301063148747 6.034738266791445 -0.25" type="box" size="0.24963643828255144 0.23840196644139286 0.26769868667385316" quat="0.9962315277104217 0.0748595687157358 -0.04339486591240896 0.005972753125429671" /><geom pos="-1.9254301063148747 6.2335717807829205 -0.25" type="box" size="0.26633590115362643 0.23598743316336385 0.24210181069763276" quat="0.9990933437841425 0.015658402764626305 -0.03627727391959475 -0.015851316224358824" /><geom pos="-1.9254301063148747 6.459392071287645 -0.25" type="box" size="0.2593192278403041 0.22927891062785205 0.22834232565114207" quat="0.9882292842185655 0.09611140992073133 -0.08077087477093627 0.08741592809464765" /><geom pos="-1.9254301063148747 6.616029008621849 -0.25" type="box" size="0.26152229123651727 0.2531362468251562 0.23313531592271358" quat="0.9965541889922205 0.07649039206305144 -0.023334954705072245 0.02201018430205244" /><geom pos="-1.7541573626892082 5.1884371443738875 -0.25" type="box" size="0.2731290300516047 0.23022180689977717 0.22857805332165673" quat="0.9966228268094148 -0.004250598079250945 -0.08133046317190054 0.010499012268971849" /><geom pos="-1.7541573626892082 5.341281408331501 -0.25" type="box" size="0.25291593204117335 0.23124356152731457 0.2277603050161706" quat="0.9943323223054082 -0.04791900646384757 -0.03860019317836129 -0.08670078849032828" /><geom pos="-1.7541573626892082 5.4934772188776595 -0.25" type="box" size="0.2337596401335252 0.26200590044701244 0.23909094918889015" quat="0.996109843857546 0.061230541842612486 0.01706983238920876 0.06102966932533433" /><geom pos="-1.7541573626892082 5.643812262182328 -0.25" type="box" size="0.24778523307740485 0.241595350565245 0.2525353314060603" quat="0.9947334460861192 0.04811420482762334 -0.00100757893361719 -0.09049518946403731" /><geom pos="-1.7541573626892082 5.863550720159648 -0.25" type="box" size="0.2532319052630184 0.2696518431964444 0.25891908203837344" quat="0.9957487341884106 -0.021786475991099834 -0.008660293388016951 -0.08907753445454497" /><geom pos="-1.7541573626892082 6.043458638503928 -0.25" type="box" size="0.2307099367641546 0.24381123783324973 0.27473240013154476" quat="0.9969458036733289 0.0767851901374366 -0.009333750983656068 -0.010769410674378053" /><geom pos="-1.7541573626892082 6.233290621463965 -0.25" type="box" size="0.2515208899411252 0.26194620150302167 0.24609042380726065" quat="0.995819706755401 0.023438391463486318 -0.0180726917200603 -0.08641256423219502" /><geom pos="-1.7541573626892082 6.454431846481093 -0.25" type="box" size="0.2641604166851643 0.2380590762732855 0.27337444857612814" quat="0.9893598138420486 0.08533897700316224 -0.05608375664370647 0.10362929122217412" /><geom pos="-1.596862546532423 5.192881177767195 -0.25" type="box" size="0.23216022224956448 0.26384945146481437 0.2724639618689737" quat="0.9981056521852645 0.054093696459227895 -0.002795746084483962 -0.02917469593733719" /><geom pos="-1.596862546532423 5.419094959840761 -0.25" type="box" size="0.2662711046306828 0.22918581617594364 0.2664239761377885" quat="0.9930630485104097 -0.06071113245337195 -0.05922685917637096 -0.08143782432962625" /><geom pos="-1.596862546532423 5.5831319325690645 -0.25" type="box" size="0.23096513044598901 0.2602144769771032 0.23097930349504253" quat="0.9961589954173549 0.01770006590573937 -0.08523321191822479 -0.009447915226205878" /><geom pos="-1.596862546532423 5.819950546627857 -0.25" type="box" size="0.2337857512678504 0.26892398171000625 0.2497026727070273" quat="0.9960349158822317 0.0195071352217872 0.017929045854563178 0.08492624643571364" /><geom pos="-1.596862546532423 5.983981603505122 -0.25" type="box" size="0.26587037372662753 0.26116834734226624 0.24907766308792137" quat="0.9970377641939235 -0.003978154322738245 -0.027434918108260885 -0.0717439637025964" /><geom pos="-1.596862546532423 6.146892696198101 -0.25" type="box" size="0.27069890455909434 0.2608084831417445 0.2566785649062772" quat="0.9962543934540666 0.012715136203309746 0.08434712488985883 -0.01417996324450968" /><geom pos="-1.596862546532423 6.385121203564222 -0.25" type="box" size="0.2485308068743382 0.22961585099099166 0.22564686802867268" quat="0.996487792094232 0.07518486535623929 0.01998948552469579 0.030979617444133477" /><geom pos="-1.596862546532423 6.538901816199414 -0.25" type="box" size="0.25897017625625973 0.2746587578986494 0.2744103173639708" quat="0.9950000210893117 0.023985064187163337 0.08748158747097946 0.04179290109293891" /><geom pos="-1.3625867825689488 5.158817084046877 -0.25" type="box" size="0.23749244585819543 0.2576577491126783 0.2665695469386044" quat="0.9985019348594072 0.0030014179602665383 0.03401571804110908 -0.04275287707740287" /><geom pos="-1.3625867825689488 5.372423803758062 -0.25" type="box" size="0.25845927426993404 0.2363640138484692 0.2373945618585948" quat="0.990386366412189 -0.087169483192327 0.08930842150149873 -0.05966851995612565" /><geom pos="-1.3625867825689488 5.618446522014384 -0.25" type="box" size="0.25150074091860136 0.2533864301607498 0.2314503831563685" quat="0.9916537338266436 -0.06191435729394286 -0.09919187349202505 0.05431810730959433" /><geom pos="-1.3625867825689488 5.827482191515282 -0.25" type="box" size="0.226633893922013 0.23196583469253892 0.24290292737925767" quat="0.9915487132695332 0.0878338518541828 -0.09512636340098125 0.008206014141765618" /><geom pos="-1.3625867825689488 6.042285615002506 -0.25" type="box" size="0.24991638622180806 0.23912154300820732 0.2445410536524864" quat="0.9970542712715001 0.049519483233048014 0.052820616831628336 0.025309748262596774" /><geom pos="-1.3625867825689488 6.222696397739468 -0.25" type="box" size="0.25692270546871226 0.23975964553903698 0.26285605163937653" quat="0.9936114272094898 0.0279686593144246 -0.09231552070126822 -0.05858268048261448" /><geom pos="-1.3625867825689488 6.443068466226609 -0.25" type="box" size="0.26569343770678255 0.2295709278158289 0.23862078918925386" quat="0.9941915412347518 -0.06835760993789454 -0.0825664791821799 0.009653653003187435" /><geom pos="-1.3625867825689488 6.677647487346439 -0.25" type="box" size="0.2660446635274981 0.26051918909835736 0.2594320600150278" quat="0.9935788765079273 0.09508364427571761 0.05645089813203749 -0.023946040352839003" /><geom pos="-1.2082441863346016 5.170015139485329 -0.25" type="box" size="0.27324248831702336 0.2728033062463492 0.2676096562151227" quat="0.9926618514831113 0.09747119027032883 -0.07019970953410949 -0.013921797970580293" /><geom pos="-1.2082441863346016 5.359161869574812 -0.25" type="box" size="0.2686649379051948 0.26651425434342285 0.2618782461150515" quat="0.9982578904803143 -0.0428169072026129 0.013088863865850866 0.03842626958341137" /><geom pos="-1.2082441863346016 5.580195114322879 -0.25" type="box" size="0.25233914189172424 0.23924726549471304 0.23897225922637613" quat="0.9963393387340954 0.06674491331586138 0.010271159575594435 0.052417000279837304" /><geom pos="-1.2082441863346016 5.767725654642367 -0.25" type="box" size="0.27168977580686765 0.25617359746109525 0.24048744717572856" quat="0.9985596575266835 0.0033262796682405013 0.05012382769222163 0.018845374001106793" /><geom pos="-1.2082441863346016 6.008904021623707 -0.25" type="box" size="0.236652981572899 0.2570948214846598 0.2642555748721238" quat="0.9912691866834739 0.06701003174405018 0.0637809621800359 0.09395234984253668" /><geom pos="-1.2082441863346016 6.198425512158625 -0.25" type="box" size="0.27272066031751013 0.264130485404604 0.2354629098995364" quat="0.9955848024853687 -0.08788625069860372 0.006848159232512169 -0.032249197097564145" /><geom pos="-1.2082441863346016 6.416405707989108 -0.25" type="box" size="0.2591119251641092 0.2605882036823304 0.2631472377925652" quat="0.9961980683763132 -0.03655665902651118 0.024951389798912732 0.07503630715343673" /><geom pos="-1.2082441863346016 6.62594274408942 -0.25" type="box" size="0.24736285875015948 0.26774650407636597 0.26524681403170003" quat="0.9946870820910394 -0.04255845151531523 0.004335433540651438 -0.09363541499799663" /><geom pos="-0.9731921718153669 5.218434050714433 -0.25" type="box" size="0.2267330139031051 0.25417277416380457 0.23052242078081137" quat="0.9965275829725208 -0.02479681411650079 0.07782516267228926 -0.016159778452975403" /><geom pos="-0.9731921718153669 5.383521624771766 -0.25" type="box" size="0.2454126127760788 0.26681461552492086 0.2326365487062508" quat="0.9975033718768002 0.05732527686753294 0.002895186379431156 -0.04113944120066792" /><geom pos="-0.9731921718153669 5.619236752628871 -0.25" type="box" size="0.2606308640390966 0.2481626211474366 0.22996621638859246" quat="0.9966770660843414 0.011984233983703128 -0.03503051136096017 -0.07255389273583357" /><geom pos="-0.9731921718153669 5.833978769901556 -0.25" type="box" size="0.25800044505139363 0.26203737135508043 0.238073827121509" quat="0.9976726907910618 -0.015320107360223219 0.059770540247304146 0.029016872311449223" /><geom pos="-0.9731921718153669 6.002803822997413 -0.25" type="box" size="0.25290449383545405 0.2737336695598944 0.2514302938926805" quat="0.9916628171549614 -0.08621122285155959 0.09577037399670897 -0.0007194381521921939" /><geom pos="-0.9731921718153669 6.201213601754684 -0.25" type="box" size="0.25560149546232447 0.2687916634386543 0.23085388933223733" quat="0.9957760047418605 0.0006634323154702487 0.08159905385228612 0.04208684649997638" /><geom pos="-0.9731921718153669 6.369478955780346 -0.25" type="box" size="0.2661703200691854 0.24106820419194971 0.2520814444001244" quat="0.9943161347403398 0.08638538876310882 -0.04675500135751274 -0.04107260219825446" /><geom pos="-0.9731921718153669 6.6108834184157335 -0.25" type="box" size="0.23684411068751596 0.27250337019903115 0.2643645025053963" quat="0.992233941615176 -0.09080266959994455 0.0842552307613352 0.0113020524547129" /><geom pos="-0.7653332439979386 5.212674212873956 -0.25" type="box" size="0.24931543322402389 0.2510162331367878 0.2671773154181361" quat="0.9955539978784441 -0.029770289005684337 0.04389166136370492 -0.07784272132639455" /><geom pos="-0.7653332439979386 5.403121696258495 -0.25" type="box" size="0.22762143229490647 0.2401871619178235 0.2546421588059245" quat="0.9951317510088776 0.08094815174298467 0.05327712088818314 -0.0179372030502547" /><geom pos="-0.7653332439979386 5.651453382638306 -0.25" type="box" size="0.2336203090445806 0.25322258464161185 0.23885320200347995" quat="0.9967371111829062 -0.05286583387797287 -0.0021487974397577728 -0.06095668518468346" /><geom pos="-0.7653332439979386 5.866374442399483 -0.25" type="box" size="0.26413866048384793 0.2604220433904193 0.26303077177953654" quat="0.9885666833740037 -0.09988886992542392 -0.045625234507557705 -0.10332697694249304" /><geom pos="-0.7653332439979386 6.0853006683993645 -0.25" type="box" size="0.22956894754291288 0.27021670507218026 0.2655421889778873" quat="0.9961149632492509 0.009270279237555357 0.07363699312101157 -0.047398683081890505" /><geom pos="-0.7653332439979386 6.278555413753501 -0.25" type="box" size="0.243819506052444 0.25158462170899804 0.26098568304512265" quat="0.995614663122201 0.08260464710451983 0.040489741155498964 0.016985161581948002" /><geom pos="-0.7653332439979386 6.502297629590165 -0.25" type="box" size="0.26801167231198686 0.2582923320194094 0.2300960767409886" quat="0.9979824833149615 -0.002418605358341994 -0.0020459209664224123 -0.06341078419340303" /><geom pos="-0.7653332439979386 6.731189366974674 -0.25" type="box" size="0.2665450905768593 0.2413270949329855 0.2250822458931138" quat="0.995313902944683 0.005387873567221003 -0.09251540708652983 0.027606247029598806" /><geom pos="-0.5378134058624615 5.2164732498217905 -0.25" type="box" size="0.23757128140513595 0.25246410369992706 0.2661539422886498" quat="0.9918333514171868 0.05622608650174435 -0.06440212216942469 0.09464458184874731" /><geom pos="-0.5378134058624615 5.4151214425302685 -0.25" type="box" size="0.27273754203921274 0.25709056529794394 0.22589036128771567" quat="0.9940272653531872 -0.0882262523294094 0.023948332499150383 -0.05960202601323106" /><geom pos="-0.5378134058624615 5.6270298047399985 -0.25" type="box" size="0.2607194581461179 0.24609535697988458 0.24439794598859163" quat="0.9921150821616632 -0.06635292292826593 -0.08977656217397972 -0.05696597449753251" /><geom pos="-0.5378134058624615 5.854464042968102 -0.25" type="box" size="0.2500776662886963 0.2700534303856564 0.22965278697990507" quat="0.9982095169639158 0.057578793221223896 0.011438363163316017 0.011471994682601407" /><geom pos="-0.5378134058624615 6.0133483283351525 -0.25" type="box" size="0.26847644075907207 0.2459581259739834 0.22620842567451094" quat="0.9899033147782317 0.09936356334412293 -0.09220422506885805 0.04143296453403689" /><geom pos="-0.5378134058624615 6.24316082085513 -0.25" type="box" size="0.2631208106662198 0.24718397334068826 0.2443355259664161" quat="0.996590395637951 -0.0034432772167115135 -0.07480342901588413 0.03464353001163109" /><geom pos="-0.5378134058624615 6.488972411387846 -0.25" type="box" size="0.2499362104762278 0.22820189265921065 0.22727180903253183" quat="0.9923942318104538 0.060847226198876024 -0.09579951895624467 0.04768391658614347" /><geom pos="-0.5378134058624615 6.7051251463557175 -0.25" type="box" size="0.2665776111054986 0.2425361892987431 0.23935949436943876" quat="0.9971002949388676 0.07178207502152119 -0.004158039505892828 0.024920799463404156" /><geom type="hfield" hfield="perlin_hfield" pos="-1.5 4.0 0.0" quat="1.0 0.0 0.0 0.0" /><geom type="hfield" hfield="image_hfield" pos="-1.5 2.0 0.0" quat="0.7073882691671998 0.0 0.0 -0.706825181105366" /></worldbody>
</mujoco>